MANIFEST.in
README.rst
requirements.txt
setup.py
spark_basic_python/__init__.py
spark_basic_python.egg-info/PKG-INFO
spark_basic_python.egg-info/SOURCES.txt
spark_basic_python.egg-info/dependency_links.txt
spark_basic_python.egg-info/top_level.txt
spark_basic_python/com/__init__.py
spark_basic_python/com/tf56/__init__.py
spark_basic_python/com/tf56/research/__init__.py
spark_basic_python/com/tf56/research/main/__init__.py
spark_basic_python/com/tf56/research/main/tag_instance.py
spark_basic_python/com/tf56/research/main/tag_values.py
spark_basic_python/com/tf56/research/main/test.py
spark_basic_python/com/tf56/research/main/test_save_to_hive.py
spark_basic_python/com/tf56/research/main/test_tag.py
spark_basic_python/com/tf56/research/main/wordcount.py
spark_basic_python/com/tf56/sparkbasic/__init__.py
spark_basic_python/com/tf56/sparkbasic/contextfactory.py
spark_basic_python/com/tf56/sparkbasic/dataaccess.py
spark_basic_python/com/tf56/sparkbasic/kfksteam.py
spark_basic_python/com/tf56/util/__init__.py
spark_basic_python/com/tf56/util/configloader.py
spark_basic_python/com/tf56/util/property.py
spark_basic_python/resources/__init__.py
spark_basic_python/resources/pg.datasource.ini
spark_basic_python/resources/sparkbasic.ini